cemaim/__init__.py
cemaim/__main__.py
cemaim/cemaim.py
cemaim/cemaim.ui
cemaim/cemaim_qt.py
cemaim/cli.py
cemaim/thb_certdb.py
cemaim/utils.py
CeMaIm-0.1.dist-info/LICENCE
CeMaIm-0.1.dist-info/METADATA
CeMaIm-0.1.dist-info/WHEEL
CeMaIm-0.1.dist-info/entry_points.txt
CeMaIm-0.1.dist-info/top_level.txt
CeMaIm-0.1.dist-info/RECORD
