Metadata-Version: 2.1
Name: CeMaIm
Version: 0.1
Summary: Program for import certificates to email client
Home-page: https://github.com/vaceklu6/certs-mail-import
Author: Lukas Vacek
Author-email: vaceklu6@fit.cvut.cz
License: GPLv3
Platform: UNKNOWN
Classifier: Programming Language :: Python
Classifier: Programming Language :: Python :: 3
Classifier: Programming Language :: Python :: 3.6
Requires-Dist: bs4
Requires-Dist: click
Requires-Dist: importlib.resources
Requires-Dist: pyOpenSSL
Requires-Dist: pycryptodome
Requires-Dist: pyqt5
Requires-Dist: requests
Requires-Dist: unicode
Requires-Dist: unidecode
